mapca/__about__.py
mapca/__init__.py
mapca/_version.py
mapca/mapca.py
mapca/utils.py
mapca/tests/__init__.py
mapca/tests/conftest.py
mapca/tests/test_integration.py
mapca/tests/test_mapca.py
mapca/tests/test_utils.py
mapca-0.0.6.dist-info/METADATA
mapca-0.0.6.dist-info/WHEEL
mapca-0.0.6.dist-info/licenses/LICENSE
mapca-0.0.6.dist-info/RECORD
