Metadata-Version: 2.4
Name: mapca
Version: 0.0.6
Summary: Moving Average Principal Component Analysis for fMRI data
Project-URL: Homepage, https://github.com/ME-ICA/mapca
Project-URL: Documentation, https://www.mapca.readthedocs.io
Author: mapca developers
License:                     GNU GENERAL PUBLIC LICENSE
License-File: LICENSE
Classifier: Development Status :: 4 - Beta
Classifier: Intended Audience :: Science/Research
Classifier: License :: OSI Approved :: GNU Library or Lesser General Public License (LGPL)
Classifier: Programming Language :: Python :: 3.8
Classifier: Programming Language :: Python :: 3.9
Classifier: Programming Language :: Python :: 3.10
Classifier: Programming Language :: Python :: 3.11
Classifier: Programming Language :: Python :: 3.12
Classifier: Topic :: Scientific/Engineering :: Information Analysis
Requires-Python: >=3.8
Requires-Dist: nibabel>=2.5.1
Requires-Dist: nilearn
Requires-Dist: numpy>=1.16
Requires-Dist: scikit-learn>=1.2
Requires-Dist: scipy>=1.3.3
Provides-Extra: all
Requires-Dist: codecov; extra == 'all'
Requires-Dist: coverage; extra == 'all'
Requires-Dist: flake8-black; extra == 'all'
Requires-Dist: flake8-isort; extra == 'all'
Requires-Dist: flake8-pyproject; extra == 'all'
Requires-Dist: flake8>=3.7; extra == 'all'
Requires-Dist: pre-commit; extra == 'all'
Requires-Dist: pytest; extra == 'all'
Requires-Dist: pytest-cov>=4.0.0; extra == 'all'
Requires-Dist: requests; extra == 'all'
Requires-Dist: sphinx-argparse; extra == 'all'
Requires-Dist: sphinx-copybutton; extra == 'all'
Requires-Dist: sphinx-rtd-theme>=1.2.2; extra == 'all'
Requires-Dist: sphinx>=6.2.1; extra == 'all'
Requires-Dist: sphinxcontrib-bibtex; extra == 'all'
Provides-Extra: dev
Requires-Dist: pre-commit; extra == 'dev'
Provides-Extra: doc
Requires-Dist: sphinx-argparse; extra == 'doc'
Requires-Dist: sphinx-copybutton; extra == 'doc'
Requires-Dist: sphinx-rtd-theme>=1.2.2; extra == 'doc'
Requires-Dist: sphinx>=6.2.1; extra == 'doc'
Requires-Dist: sphinxcontrib-bibtex; extra == 'doc'
Provides-Extra: tests
Requires-Dist: codecov; extra == 'tests'
Requires-Dist: coverage; extra == 'tests'
Requires-Dist: flake8-black; extra == 'tests'
Requires-Dist: flake8-isort; extra == 'tests'
Requires-Dist: flake8-pyproject; extra == 'tests'
Requires-Dist: flake8>=3.7; extra == 'tests'
Requires-Dist: pytest; extra == 'tests'
Requires-Dist: pytest-cov>=4.0.0; extra == 'tests'
Requires-Dist: requests; extra == 'tests'
